metricflow_to_zenlytic/__init__.py
metricflow_to_zenlytic/cli.py
metricflow_to_zenlytic/metricflow_to_zenlytic.py
metricflow_to_zenlytic/metricflow_types.py
metricflow_to_zenlytic-0.1.5.dist-info/LICENSE
metricflow_to_zenlytic-0.1.5.dist-info/METADATA
metricflow_to_zenlytic-0.1.5.dist-info/WHEEL
metricflow_to_zenlytic-0.1.5.dist-info/entry_points.txt
metricflow_to_zenlytic-0.1.5.dist-info/RECORD
