Metadata-Version: 2.1
Name: metricflow-to-zenlytic
Version: 0.1.5
Summary: Adapter for Metricflow to Zenlytic
Home-page: https://github.com/Zenlytic/zenlytic-adapters
License: MIT
Keywords: Metrics Layer,Business Intelligence,Analytics
Author: Paul Blankley
Author-email: paul@zenlytic.com
Requires-Python: >=3.8.1,<3.14
Classifier: License :: OSI Approved :: MIT License
Classifier: Programming Language :: Python :: 3
Classifier: Programming Language :: Python :: 3.9
Classifier: Programming Language :: Python :: 3.10
Classifier: Programming Language :: Python :: 3.11
Classifier: Programming Language :: Python :: 3.12
Requires-Dist: click (>=8.0,<9.0)
Requires-Dist: ruamel.yaml (>=0.17.20,<0.18.0)
Project-URL: Documentation, https://github.com/Zenlytic/zenlytic-adapters
Project-URL: Repository, https://github.com/Zenlytic/zenlytic-adapters
